databricks_bridge/__init__.py
databricks_bridge-0.0.6.dist-info/METADATA
databricks_bridge-0.0.6.dist-info/WHEEL
databricks_bridge-0.0.6.dist-info/top_level.txt
databricks_bridge-0.0.6.dist-info/RECORD
