Metadata-Version: 2.1
Name: databricks-bridge
Version: 0.0.6
Summary: Databricks read and write with sql connection
Home-page: UNKNOWN
Author: Y-Tree (Saeed Falowo)
Author-email: saeed@y-tree.com
License: UNKNOWN
Keywords: python,databricks,pyspark,sql,dataframe
Platform: UNKNOWN
Classifier: Development Status :: 4 - Beta
Classifier: Intended Audience :: Developers
Classifier: Programming Language :: Python :: 3
Classifier: Operating System :: Unix
Classifier: Operating System :: MacOS :: MacOS X
Classifier: Operating System :: Microsoft :: Windows
Requires-Dist: pandas
Requires-Dist: numpy
Requires-Dist: databricks-sql-connector
Requires-Dist: pyspark
